{"identifier":"biw.BIWAPP-90480_NGRjZTkwNzI3NzRkZTBmNA","sender":"CAP@biwapp.de","sent":"2025-08-28T15:50:08+02:00","status":"Actual","msgType":"Update","scope":"Public","code":["DVN:7","BIWAPP"],"references":"biw.BIWAPP-90480_MmI2ZTRkMjY4ZmVkMWU3Yg biw.BIWAPP-90480_NTQzYmQxYjEwZTU2NzNhZQ","info":[{"language":"DE","category":["Safety"],"event":"8","urgency":"Unknown","severity":"Minor","certainty":"Unknown","expires":"2025-09-19T23:59:00+02:00","headline":"Erhöhtes Blaualgen-Vorkommen: Badeverbot am Dreiburgensee","description":"Fürstenzell/Tittling. Bei der letzten Beprobung des Dreiburgensees (Markt Tittling) wurde erneut eine verstärkte Blaualgenbildung festgestellt. Die Laborergebnisse dieser Gewässeruntersuchung zeigen eine deutlich erhöhte Konzentration an verschiedenen Blaualgen. Blaualgen können sog. Cyanotoxine bilden, also Giftstoffe. Für Badende kann von diesen Giftstoffen ein Gesundheitsrisiko ausgehen. Das Gesundheitsamt hat deshalb für den Dreiburgensee bis auf Weiteres ein Badeverbot ausgesprochen.<br><br>Die Giftstoffe der Blaualgen können sowohl beim Menschen als auch bei Tieren Vergiftungssymptome hervorrufen, insbesondere Übelkeit, Erbrechen, Durchfall, Fieber sowie Reizungen der Nasen- und Rachenschleimhäute. Vor allem nach dem Verschlucken von Wasser können diese Beschwerden auftreten. Ebenso können beim Kontakt mit dem Wasser Hautreizungen, Entzündungen oder Ausschläge ausgelöst werden.<br><br>Weitere Beprobungen des Badewassers erfolgen durch das Gesundheitsamt in den nächsten Wochen.<br>&nbsp;","parameter":[{"valueName":"sender_langname","value":"Landratsamt Passau Pressestelle"},{"valueName":"PHGEM","value":"8446,8673,100001"},{"valueName":"GRID","value":"387303,500001"}],"area":[{"areaDesc":"Thurmansbang, Tittling","geocode":[{"valueName":"AreaId","value":"0"}]}]}]}